solid_node/__init__.py
solid_node/cli.py
solid_node/exceptions.py
solid_node/manager.py
solid_node/node/__init__.py
solid_node/node/base.py
solid_node/node/cq_node.py
solid_node/node/internal.py
solid_node/node/leaf.py
solid_node/node/solid2_node.py
solid_node/node/spatial.py
solid_node-0.0.1.dist-info/LICENSE
solid_node-0.0.1.dist-info/METADATA
solid_node-0.0.1.dist-info/WHEEL
solid_node-0.0.1.dist-info/entry_points.txt
solid_node-0.0.1.dist-info/top_level.txt
solid_node-0.0.1.dist-info/RECORD
