Metadata-Version: 2.1
Name: solid-node
Version: 0.0.1
Summary: A framework to develop and manage solid projects in Python
Home-page: https://github.com/lfagundes/solid_node
Author: Luis Fagundes
Author-email: lhfagundes@gmail.com
License: GNU Affero General Public License v3 or later
Keywords: solid_node
Classifier: Development Status :: 2 - Pre-Alpha
Classifier: Intended Audience :: Developers
Classifier: Natural Language :: English
Classifier: Programming Language :: Python :: 3
Classifier: Programming Language :: Python :: 3.6
Classifier: Programming Language :: Python :: 3.7
Classifier: Programming Language :: Python :: 3.8
Requires-Python: >=3.6
License-File: LICENSE
